fast_pdf_gen/__init__.py
fast_pdf_gen/handlebars_compiler.py
fast_pdf_gen/pdf_generator.py
tests/__init__.py
tests/test_fast_pdf_gen.py
fast_pdf_gen-1.0.0.dist-info/METADATA
fast_pdf_gen-1.0.0.dist-info/WHEEL
fast_pdf_gen-1.0.0.dist-info/top_level.txt
fast_pdf_gen-1.0.0.dist-info/RECORD
