Metadata-Version: 2.1
Name: fast-pdf-gen
Version: 1.0.0
Summary: A fast PDF generation package using Handlebars templates
Home-page: https://github.com/saadhoucem/fast_pdf_gen
Author: Houcem Eddine Saad
Author-email: houcemsaad@gmail.com
Classifier: Development Status :: 3 - Alpha
Classifier: Intended Audience :: Developers
Classifier: License :: OSI Approved :: MIT License
Classifier: Programming Language :: Python :: 3
Classifier: Programming Language :: Python :: 3.6
Classifier: Programming Language :: Python :: 3.7
Classifier: Programming Language :: Python :: 3.8
Classifier: Programming Language :: Python :: 3.9
Classifier: Programming Language :: Python :: 3.10
Classifier: Programming Language :: Python :: 3.11
Classifier: Programming Language :: Python :: 3.12
Classifier: Operating System :: OS Independent
Requires-Dist: pybars3
Requires-Dist: pyppeteer
